megadetector/__init__.py
megadetector/api/__init__.py
megadetector/api/batch_processing/integration/digiKam/setup.py
megadetector/api/batch_processing/integration/digiKam/xmp_integration.py
megadetector/api/batch_processing/integration/eMammal/test_scripts/config_template.py
megadetector/api/batch_processing/integration/eMammal/test_scripts/push_annotations_to_emammal.py
megadetector/api/batch_processing/integration/eMammal/test_scripts/select_images_for_testing.py
megadetector/classification/__init__.py
megadetector/classification/aggregate_classifier_probs.py
megadetector/classification/analyze_failed_images.py
megadetector/classification/cache_batchapi_outputs.py
megadetector/classification/create_classification_dataset.py
megadetector/classification/crop_detections.py
megadetector/classification/csv_to_json.py
megadetector/classification/detect_and_crop.py
megadetector/classification/evaluate_model.py
megadetector/classification/identify_mislabeled_candidates.py
megadetector/classification/json_to_azcopy_list.py
megadetector/classification/json_validator.py
megadetector/classification/map_classification_categories.py
megadetector/classification/merge_classification_detection_output.py
megadetector/classification/prepare_classification_script.py
megadetector/classification/prepare_classification_script_mc.py
megadetector/classification/run_classifier.py
megadetector/classification/save_mislabeled.py
megadetector/classification/train_classifier.py
megadetector/classification/train_classifier_tf.py
megadetector/classification/train_utils.py
megadetector/classification/efficientnet/__init__.py
megadetector/classification/efficientnet/model.py
megadetector/classification/efficientnet/utils.py
megadetector/data_management/__init__.py
megadetector/data_management/animl_to_md.py
megadetector/data_management/camtrap_dp_to_coco.py
megadetector/data_management/cct_json_utils.py
megadetector/data_management/cct_to_md.py
megadetector/data_management/cct_to_wi.py
megadetector-10.0.17.dist-info/licenses/LICENSE
megadetector-10.0.17.dist-info/METADATA
megadetector-10.0.17.dist-info/WHEEL
megadetector-10.0.17.dist-info/top_level.txt
megadetector-10.0.17.dist-info/RECORD
